azcex/__init__.py
azcex/bitget/__init__.py
azcex/bn/__init__.py
azcex/bybit/__init__.py
azcex/gateio/__init__.py
azcex/okx/__init__.py
azcex/py.typed
azcex-0.1.0.dist-info/WHEEL
azcex-0.1.0.dist-info/METADATA
azcex-0.1.0.dist-info/RECORD
