Metadata-Version: 2.3
Name: azcex
Version: 0.1.0
Summary: Add your description here
Keywords: python cex libs,cex,Python Centralized Crypto Exchange Libs
Author: hhglory
Author-email: hhglory <hhglory@outlook.com>
Requires-Dist: loguru>=0.7.3
Requires-Python: >=3.12
